superseal/__init__.py
superseal/assembly.py
superseal/cli.py
superseal/graph.py
superseal/io.py
superseal/reads.py
superseal/regression.py
superseal/viz.py
superseal/viz/.gitignore
superseal/viz/favicon.ico
superseal/viz/index.html
superseal/viz/logo.png
superseal/viz/main.js
superseal/viz/style.css
superseal/viz/superreads.json
superseal/viz/test-superreads.json
superseal-0.0.1.post1.dist-info/LICENSE
superseal-0.0.1.post1.dist-info/METADATA
superseal-0.0.1.post1.dist-info/WHEEL
superseal-0.0.1.post1.dist-info/entry_points.txt
superseal-0.0.1.post1.dist-info/top_level.txt
superseal-0.0.1.post1.dist-info/RECORD
